{
  "palabras_reservadas": [
    { "token": "inicio", "original": "inicio" },
    { "token": "fin", "original": "fin" },
    { "token": "var", "original": "var" },
    { "token": "ChicoEntero", "original": "int" },
    { "token": "Flotante", "original": "float" },
    { "token": "doble", "original": "double" },
    { "token": "VerdaderoOFalso", "original": "boolean" },
    { "token": "string", "original": "string" },
    { "token": "Letra", "original": "char" },
    { "token": "PreguntaExistencial", "original": "if" },
    { "token": "PuesSiNo", "original": "else" },
    { "token": "Mientras", "original": "while" },
    { "token": "Cuatro", "original": "for" },
    { "token": "DoMientras", "original": "do while" },
    { "token": "intenta", "original": "try" },
    { "token": "AgarraElError", "original": "catch" },
    { "token": "switch", "original": "switch" },
    { "token": "Opcion", "original": "case" },
    { "token": "default", "original": "default" },
    { "token": "Clase", "original": "class" },
    { "token": "verdad", "original": "true" },
    { "token": "fake", "original": "false" }
  ],
  "operadores_aritmeticos": [
    "+", "-", "*", "/"
  ],
  "operadores_asignacion": [
    "="
  ],
  "operadores_comparacion": [
    "==", "!=", "<", "<=", ">", ">="
  ],
  "operadores_logicos": [
    "&&", "||"
  ],
  "simbolos_puntuacion": [
    ":", ";", ",", "¿", "?", "[", "]"
  ]
}